evalgit/__main__.py
evalgit/core/__init__.py
evalgit/core/cli.py
evalgit/core/db.py
evalgit/core/io.py
evalgit/core/log.py
evalgit/core/metrics.py
evalgit/core/report.py
evalgit-0.1.0.dist-info/licenses/LICENSE
evalgit-0.1.0.dist-info/METADATA
evalgit-0.1.0.dist-info/WHEEL
evalgit-0.1.0.dist-info/entry_points.txt
evalgit-0.1.0.dist-info/top_level.txt
evalgit-0.1.0.dist-info/RECORD
