Metadata-Version: 2.4
Name: evalgit
Version: 0.1.0
Summary: CLI tool for locally tracking and reporting machine learning evaluation metrics.
Author-email: Fadl Ghaddar <fadl2009gh@gmail.com>
License-Expression: Apache-2.0
Requires-Python: >=3.8
License-File: LICENSE
Dynamic: license-file
